{
  "id": "01_sedan_1940",
  "title": "色當突破 1940",
  "briefing": "1940 年 5 月 13 日。古德林的第 19 裝甲軍剛通過阿登森林,正壓向馬士河畔的色當。法軍第 55 步兵師沿河防守,但反應遲緩、缺乏裝甲縱深。\n\n你的任務:在 12 個回合內,以裝甲先鋒突破馬士河防線並佔領色當鎮(西側目標城鎮)。法軍只要拖到時限便算勝利。\n\n戰術提示:法軍佔住城鎮和森林獲得地形加成;反戰車砲在開闊地依然致命。\n保持你的中戰車並善用機動性側翼。北方那幾座山是你剛穿越的阿登高地 — 可以繞,別硬鑽。",
  "map": {
    "width": 14,
    "height": 10,
    "tiles": [
      ["plain", "plain", "plain", "road",   "road",   "road",   "plain",  "plain",  "mountain","mountain","forest", "forest", "forest", "forest"],
      ["plain", "town",  "plain", "plain",  "plain",  "plain",  "plain",  "forest", "forest", "mountain","forest", "forest", "forest", "forest"],
      ["plain", "plain", "plain", "road",   "plain",  "plain",  "river",  "plain",  "plain",  "forest", "forest", "forest", "forest", "forest"],
      ["plain", "forest","plain", "road",   "plain",  "river",  "river",  "plain",  "plain",  "plain",  "forest", "forest", "forest", "forest"],
      ["plain", "forest","plain", "plain",  "river",  "river",  "plain",  "plain",  "plain",  "plain",  "forest", "forest", "forest", "forest"],
      ["plain", "plain", "plain", "river",  "river",  "plain",  "plain",  "plain",  "road",   "road",   "road",   "road",   "forest", "forest"],
      ["plain", "plain", "river", "river",  "plain",  "plain",  "plain",  "plain",  "plain",  "plain",  "plain",  "plain",  "plain",  "forest"],
      ["plain", "river", "river", "plain",  "plain",  "plain",  "forest", "plain",  "plain",  "plain",  "plain",  "plain",  "plain",  "plain"],
      ["plain", "plain", "plain", "plain",  "forest", "forest", "forest", "plain",  "plain",  "plain",  "town",   "plain",  "plain",  "plain"],
      ["plain", "plain", "plain", "plain",  "plain",  "plain",  "plain",  "plain",  "plain",  "plain",  "plain",  "plain",  "plain",  "plain"]
    ]
  },
  "factions": [
    {"id": "axis",   "name": "德軍裝甲軍",   "controller": "player", "color": "#a86632"},
    {"id": "allies", "name": "法軍第 55 師", "controller": "ai", "ai": "defensive", "color": "#2f6fb0"}
  ],
  "units": [
    {"faction": "axis", "type": "medium_tank", "name": "Pz.IV",     "at": [12, 0], "general": "guderian"},
    {"faction": "axis", "type": "medium_tank", "name": "Pz.III a",  "at": [13, 2]},
    {"faction": "axis", "type": "medium_tank", "name": "Pz.III b",  "at": [12, 4]},
    {"faction": "axis", "type": "light_tank",  "name": "Pz.II",     "at": [11, 6]},
    {"faction": "axis", "type": "infantry",    "name": "擲彈兵 1",  "at": [13, 7]},
    {"faction": "axis", "type": "infantry",    "name": "擲彈兵 2",  "at": [13, 9]},
    {"faction": "axis", "type": "artillery",   "name": "150 mm",    "at": [13, 5]},

    {"faction": "allies", "type": "infantry",  "name": "法步 1",   "at": [1, 1]},
    {"faction": "allies", "type": "mg_team",   "name": "Hotchkiss","at": [3, 3]},
    {"faction": "allies", "type": "infantry",  "name": "法步 2",   "at": [1, 4]},
    {"faction": "allies", "type": "at_gun",    "name": "25 mm AT", "at": [4, 5]},
    {"faction": "allies", "type": "mg_team",   "name": "MG 8",     "at": [3, 7]},
    {"faction": "allies", "type": "infantry",  "name": "法步 3",   "at": [10, 8], "general": "de_gaulle"}
  ],
  "victory": {
    "axis":   {"type": "capture", "target": [10, 8], "by_turn": 12},
    "allies": {"type": "survive", "by_turn": 12}
  }
}
